{
    "IIITH-Problem_Solving.JPG": {
        "contentType": "image/jpeg", 
        "content_son": {
            "category": "asset", 
            "course": "cse04", 
            "name": "IIITH-Problem_Solving.JPG", 
            "org": "Virtual-Labs", 
            "revision": null, 
            "run": "Anytime", 
            "tag": "c4x"
        }, 
        "displayname": "IIITH-Problem Solving.JPG", 
        "filename": "asset-v1:Virtual-Labs+cse04+Anytime+type@asset+block@IIITH-Problem_Solving.JPG", 
        "import_path": "IIITH-Problem Solving.JPG", 
        "locked": false, 
        "thumbnail_location": [
            "c4x", 
            "Virtual-Labs", 
            "cse04", 
            "thumbnail", 
            "IIITH-Problem_Solving-JPG.jpg", 
            null
        ]
    }
}